skyler_cli/__init__.py
skyler_cli/cli/__init__.py
skyler_cli/cli/main.py
skyler_cli/core/__init__.py
skyler_cli/core/bootstrap/__init__.py
skyler_cli/core/bootstrap/system.py
skyler_cli/core/bootstrap/system_template/.bashrc
skyler_cli/core/bootstrap/system_template/__init__.py
skyler_cli/core/bootstrap/system_template/compton.conf
skyler_cli/core/bootstrap/system_template/i3_config
skyler_cli/core/bootstrap/system_template/inputrc
skyler_cli/core/bootstrap/system_template/tmux.conf
skyler_cli-0.8.0.dist-info/METADATA
skyler_cli-0.8.0.dist-info/WHEEL
skyler_cli-0.8.0.dist-info/entry_points.txt
skyler_cli-0.8.0.dist-info/RECORD
